jeeves_pr_stack/__init__.py
jeeves_pr_stack/app.py
jeeves_pr_stack/errors.py
jeeves_pr_stack/format.py
jeeves_pr_stack/github.py
jeeves_pr_stack/logic.py
jeeves_pr_stack/models.py
jeeves_pr_stack-0.1.6.dist-info/METADATA
jeeves_pr_stack-0.1.6.dist-info/WHEEL
jeeves_pr_stack-0.1.6.dist-info/entry_points.txt
jeeves_pr_stack-0.1.6.dist-info/RECORD
